[
  {
    "name": "Appetizers",
    "iconUrl": "https://ik.imagekit.io/13x54r/Momo2Go/apetizers.png?updatedAt=1688184823368"
  },
  {
    "name": "Himalayan Mo:Mo's",
    "iconUrl": "https://ik.imagekit.io/13x54r/Momo2Go/himalayan-momos.png?updatedAt=1688186185734"
  },
  {
    "name": "Chef's Special Mo:Mo's",
    "iconUrl": "https://ik.imagekit.io/13x54r/Momo2Go/chef-special.png?updatedAt=1688186388416"
  },
  {
    "name": "Vegetarian Entrees",
    "iconUrl": "https://ik.imagekit.io/13x54r/Momo2Go/vegetarian-entree.png?updatedAt=1688188333724"
  },
  {
    "name": "Chaap Corner",
    "iconUrl": "https://ik.imagekit.io/13x54r/Momo2Go/chaap.png?updatedAt=1688189098064"
  },
  {
    "name": "Chillis",
    "iconUrl": "https://ik.imagekit.io/13x54r/Momo2Go/chillis.png?updatedAt=1688189414533"
  },
  {
    "name": "Noodles & Rice",
    "iconUrl": "https://ik.imagekit.io/13x54r/Momo2Go/noodles.png?updatedAt=1688189485982"
  },
  {
    "name": "Curries",
    "iconUrl": "https://ik.imagekit.io/13x54r/Momo2Go/curries.png?updatedAt=1688189559125"
  },
  {
    "name": "Side Orders",
    "iconUrl": "https://ik.imagekit.io/13x54r/Momo2Go/sides.png?updatedAt=1688189716492"
  },
  {
    "name": "Drinks",
    "iconUrl": "https://ik.imagekit.io/13x54r/Momo2Go/drinks.png?updatedAt=1688190184389"
  },
  {
    "name": "Himalayan Thali Specials",
    "iconUrl": "https://ik.imagekit.io/13x54r/Momo2Go/thali.png?updatedAt=1688190416413"
  }
]
